{
    "metadata": {
        "video_path": "C:/Users/cesar/OneDrive - Instituto Tecnologico y de Estudios Superiores de Monterrey/Maestr\u00eda/Tesis/Videos/Clips/player5/part2/player5_part2_clip41_grade6.mp4",
        "video_name": "player5_part2_clip41_grade6",
        "player_id": 5,
        "part": 2,
        "clip": 41,
        "grade": 6,
        "duration": 3.003,
        "fps": 29.97002997002997,
        "frame_width": 1080,
        "frame_height": 1920,
        "total_frames": 90,
        "model": "mobilenet_thin",
        "resize": "0x0",
        "resize_out_ratio": 4.0,
        "reference_point": "Pelvis",
        "keypoints_used": [
            "Pelvis",
            "Right Elbow",
            "Right Wrist"
        ],
        "processing_date": "2025-12-04T03:51:35.263038"
    },
    "Pelvis": [
        [
            464,
            916
        ],
        [
            1064,
            357
        ],
        [
            460,
            926
        ],
        [
            460,
            926
        ],
        [
            462,
            923
        ],
        [
            460,
            922
        ],
        [
            462,
            919
        ],
        [
            460,
            919
        ],
        [
            460,
            922
        ],
        [
            456,
            919
        ],
        [
            474,
            960
        ],
        [
            478,
            957
        ],
        [
            490,
            944
        ],
        [
            498,
            944
        ],
        [
            502,
            940
        ],
        [
            508,
            956
        ],
        [
            510,
            948
        ],
        [
            510,
            957
        ],
        [
            518,
            956
        ],
        [
            514,
            957
        ],
        [
            516,
            1026
        ],
        [
            520,
            949
        ],
        [
            526,
            952
        ],
        [
            530,
            948
        ],
        [
            532,
            946
        ],
        [
            536,
            948
        ],
        [
            538,
            946
        ],
        [
            540,
            948
        ],
        [
            542,
            944
        ],
        [
            544,
            946
        ],
        [
            546,
            944
        ],
        [
            548,
            946
        ],
        [
            550,
            948
        ],
        [
            552,
            948
        ],
        [
            554,
            953
        ],
        [
            554,
            957
        ],
        [
            552,
            952
        ],
        [
            550,
            949
        ],
        [
            552,
            940
        ],
        [
            554,
            942
        ],
        [
            558,
            944
        ],
        [
            560,
            944
        ],
        [
            562,
            944
        ],
        [
            564,
            946
        ],
        [
            566,
            944
        ],
        [
            570,
            952
        ],
        [
            572,
            948
        ],
        [
            576,
            944
        ],
        [
            578,
            944
        ],
        [
            582,
            940
        ],
        [
            586,
            940
        ],
        [
            592,
            942
        ],
        [
            598,
            944
        ],
        [
            600,
            944
        ],
        [
            604,
            942
        ],
        [
            604,
            942
        ],
        [
            604,
            942
        ],
        [
            604,
            942
        ],
        [
            606,
            942
        ],
        [
            604,
            940
        ],
        [
            606,
            940
        ],
        [
            606,
            936
        ],
        [
            608,
            936
        ],
        [
            608,
            934
        ],
        [
            606,
            930
        ],
        [
            604,
            930
        ]
    ],
    "Mano Derecha Original": [
        [
            436,
            938
        ],
        [
            1062,
            375
        ],
        [
            426,
            974
        ],
        [
            418,
            968
        ],
        [
            424,
            988
        ],
        [
            422,
            991
        ],
        [
            418,
            998
        ],
        [
            370,
            1004
        ],
        [
            372,
            1013
        ],
        [
            368,
            1026
        ],
        [
            404,
            1074
        ],
        [
            410,
            1074
        ],
        [
            416,
            1050
        ],
        [
            454,
            1086
        ],
        [
            448,
            1094
        ],
        [
            450,
            1098
        ],
        [
            454,
            1100
        ],
        [
            458,
            1104
        ],
        [
            468,
            1104
        ],
        [
            456,
            1046
        ],
        [
            472,
            1108
        ],
        [
            474,
            1108
        ],
        [
            470,
            1046
        ],
        [
            472,
            1048
        ],
        [
            480,
            1048
        ],
        [
            484,
            1048
        ],
        [
            488,
            1048
        ],
        [
            492,
            1046
        ],
        [
            498,
            1048
        ],
        [
            502,
            1054
        ],
        [
            510,
            1059
        ],
        [
            522,
            1058
        ],
        [
            510,
            1119
        ],
        [
            510,
            1122
        ],
        [
            514,
            1122
        ],
        [
            522,
            1118
        ],
        [
            532,
            1108
        ],
        [
            546,
            961
        ],
        [
            512,
            1058
        ],
        [
            488,
            1054
        ],
        [
            478,
            1038
        ],
        [
            470,
            1024
        ],
        [
            478,
            1004
        ],
        [
            500,
            986
        ],
        [
            532,
            968
        ],
        [
            566,
            964
        ],
        [
            594,
            964
        ],
        [
            618,
            972
        ],
        [
            630,
            983
        ],
        [
            640,
            990
        ],
        [
            646,
            994
        ],
        [
            648,
            998
        ],
        [
            646,
            996
        ],
        [
            648,
            994
        ],
        [
            644,
            990
        ],
        [
            640,
            986
        ],
        [
            638,
            980
        ],
        [
            632,
            972
        ],
        [
            623,
            966
        ],
        [
            614,
            960
        ],
        [
            608,
            953
        ],
        [
            600,
            952
        ],
        [
            600,
            948
        ],
        [
            596,
            946
        ],
        [
            596,
            944
        ],
        [
            594,
            944
        ]
    ],
    "Mano Derecha Referencia": [
        [
            -28,
            22
        ],
        [
            -2,
            18
        ],
        [
            -34,
            48
        ],
        [
            -42,
            42
        ],
        [
            -38,
            65
        ],
        [
            -38,
            69
        ],
        [
            -44,
            79
        ],
        [
            -90,
            85
        ],
        [
            -88,
            91
        ],
        [
            -88,
            107
        ],
        [
            -70,
            114
        ],
        [
            -68,
            117
        ],
        [
            -74,
            106
        ],
        [
            -44,
            142
        ],
        [
            -54,
            154
        ],
        [
            -58,
            142
        ],
        [
            -56,
            152
        ],
        [
            -52,
            147
        ],
        [
            -50,
            148
        ],
        [
            -58,
            89
        ],
        [
            -44,
            82
        ],
        [
            -46,
            159
        ],
        [
            -56,
            94
        ],
        [
            -58,
            100
        ],
        [
            -52,
            102
        ],
        [
            -52,
            100
        ],
        [
            -50,
            102
        ],
        [
            -48,
            98
        ],
        [
            -44,
            104
        ],
        [
            -42,
            108
        ],
        [
            -36,
            115
        ],
        [
            -26,
            112
        ],
        [
            -40,
            171
        ],
        [
            -42,
            174
        ],
        [
            -40,
            169
        ],
        [
            -32,
            161
        ],
        [
            -20,
            156
        ],
        [
            -4,
            12
        ],
        [
            -40,
            118
        ],
        [
            -66,
            112
        ],
        [
            -80,
            94
        ],
        [
            -90,
            80
        ],
        [
            -84,
            60
        ],
        [
            -64,
            40
        ],
        [
            -34,
            24
        ],
        [
            -4,
            12
        ],
        [
            22,
            16
        ],
        [
            42,
            28
        ],
        [
            52,
            39
        ],
        [
            58,
            50
        ],
        [
            60,
            54
        ],
        [
            56,
            56
        ],
        [
            48,
            52
        ],
        [
            48,
            50
        ],
        [
            40,
            48
        ],
        [
            36,
            44
        ],
        [
            34,
            38
        ],
        [
            28,
            30
        ],
        [
            17,
            24
        ],
        [
            10,
            20
        ],
        [
            2,
            13
        ],
        [
            -6,
            16
        ],
        [
            -8,
            12
        ],
        [
            -12,
            12
        ],
        [
            -10,
            14
        ],
        [
            -10,
            14
        ]
    ],
    "Codo Derecha Original": [
        [
            440,
            986
        ],
        [
            1058,
            378
        ],
        [
            434,
            986
        ],
        [
            440,
            991
        ],
        [
            442,
            998
        ],
        [
            444,
            991
        ],
        [
            442,
            996
        ],
        [
            426,
            1002
        ],
        [
            416,
            1004
        ],
        [
            408,
            1010
        ],
        [
            442,
            1100
        ],
        [
            448,
            1096
        ],
        [
            442,
            1020
        ],
        [
            474,
            1082
        ],
        [
            476,
            1084
        ],
        [
            472,
            1089
        ],
        [
            474,
            1096
        ],
        [
            478,
            1098
        ],
        [
            482,
            1098
        ],
        [
            486,
            1020
        ],
        [
            488,
            1098
        ],
        [
            494,
            1096
        ],
        [
            500,
            1018
        ],
        [
            498,
            1021
        ],
        [
            504,
            1020
        ],
        [
            506,
            1024
        ],
        [
            512,
            1021
        ],
        [
            516,
            1021
        ],
        [
            518,
            1028
        ],
        [
            524,
            1028
        ],
        [
            526,
            1036
        ],
        [
            532,
            1042
        ],
        [
            532,
            1089
        ],
        [
            536,
            1086
        ],
        [
            540,
            1086
        ],
        [
            540,
            1086
        ],
        [
            546,
            1082
        ],
        [
            546,
            991
        ],
        [
            522,
            1038
        ],
        [
            510,
            1034
        ],
        [
            512,
            1028
        ],
        [
            512,
            1024
        ],
        [
            524,
            1016
        ],
        [
            534,
            1008
        ],
        [
            540,
            999
        ],
        [
            552,
            990
        ],
        [
            564,
            988
        ],
        [
            578,
            986
        ],
        [
            588,
            986
        ],
        [
            600,
            983
        ],
        [
            606,
            983
        ],
        [
            614,
            983
        ],
        [
            614,
            980
        ],
        [
            614,
            978
        ],
        [
            610,
            976
        ],
        [
            602,
            972
        ],
        [
            596,
            969
        ],
        [
            590,
            969
        ],
        [
            582,
            972
        ],
        [
            576,
            972
        ],
        [
            572,
            974
        ],
        [
            570,
            972
        ],
        [
            566,
            972
        ],
        [
            564,
            969
        ],
        [
            564,
            968
        ],
        [
            564,
            966
        ]
    ],
    "Codo Derecha Referencia": [
        [
            -24,
            70
        ],
        [
            -6,
            21
        ],
        [
            -26,
            60
        ],
        [
            -20,
            65
        ],
        [
            -20,
            75
        ],
        [
            -16,
            69
        ],
        [
            -20,
            77
        ],
        [
            -34,
            83
        ],
        [
            -44,
            82
        ],
        [
            -48,
            91
        ],
        [
            -32,
            140
        ],
        [
            -30,
            139
        ],
        [
            -48,
            76
        ],
        [
            -24,
            138
        ],
        [
            -26,
            144
        ],
        [
            -36,
            133
        ],
        [
            -36,
            148
        ],
        [
            -32,
            141
        ],
        [
            -36,
            142
        ],
        [
            -28,
            63
        ],
        [
            -28,
            72
        ],
        [
            -26,
            147
        ],
        [
            -26,
            66
        ],
        [
            -32,
            73
        ],
        [
            -28,
            74
        ],
        [
            -30,
            76
        ],
        [
            -26,
            75
        ],
        [
            -24,
            73
        ],
        [
            -24,
            84
        ],
        [
            -20,
            82
        ],
        [
            -20,
            92
        ],
        [
            -16,
            96
        ],
        [
            -18,
            141
        ],
        [
            -16,
            138
        ],
        [
            -14,
            133
        ],
        [
            -14,
            129
        ],
        [
            -6,
            130
        ],
        [
            -4,
            42
        ],
        [
            -30,
            98
        ],
        [
            -44,
            92
        ],
        [
            -46,
            84
        ],
        [
            -48,
            80
        ],
        [
            -38,
            72
        ],
        [
            -30,
            62
        ],
        [
            -26,
            55
        ],
        [
            -18,
            38
        ],
        [
            -8,
            40
        ],
        [
            2,
            42
        ],
        [
            10,
            42
        ],
        [
            18,
            43
        ],
        [
            20,
            43
        ],
        [
            22,
            41
        ],
        [
            16,
            36
        ],
        [
            14,
            34
        ],
        [
            6,
            34
        ],
        [
            -2,
            30
        ],
        [
            -8,
            27
        ],
        [
            -14,
            27
        ],
        [
            -24,
            30
        ],
        [
            -28,
            32
        ],
        [
            -34,
            34
        ],
        [
            -36,
            36
        ],
        [
            -42,
            36
        ],
        [
            -44,
            35
        ],
        [
            -42,
            38
        ],
        [
            -40,
            36
        ]
    ],
    "timestamps": [
        0.03336666666666667,
        0.16683333333333333,
        0.20020000000000002,
        0.23356666666666667,
        0.26693333333333336,
        0.3003,
        0.33366666666666667,
        0.4337666666666667,
        0.46713333333333334,
        0.5005000000000001,
        0.8008000000000001,
        0.8341666666666667,
        0.9676333333333333,
        1.1011,
        1.1344666666666667,
        1.1678333333333333,
        1.2012,
        1.2345666666666668,
        1.2679333333333334,
        1.3013000000000001,
        1.3346666666666667,
        1.3680333333333334,
        1.4014000000000002,
        1.4347666666666667,
        1.5015,
        1.5348666666666668,
        1.5682333333333334,
        1.6016000000000001,
        1.6349666666666667,
        1.6683333333333334,
        1.7017,
        1.7350666666666668,
        1.7684333333333335,
        1.8018000000000003,
        1.8351666666666668,
        1.8685333333333334,
        1.9019000000000001,
        1.9352666666666667,
        2.0687333333333333,
        2.1021,
        2.135466666666667,
        2.1688333333333336,
        2.2022,
        2.2355666666666667,
        2.2689333333333335,
        2.3023000000000002,
        2.3356666666666666,
        2.3690333333333333,
        2.4024,
        2.435766666666667,
        2.4691333333333336,
        2.5025,
        2.5358666666666667,
        2.5692333333333335,
        2.6026000000000002,
        2.635966666666667,
        2.6693333333333333,
        2.7027,
        2.736066666666667,
        2.7694333333333336,
        2.8028000000000004,
        2.8361666666666667,
        2.8695333333333335,
        2.9029000000000003,
        2.936266666666667,
        2.9696333333333333
    ],
    "total_coordinates": 66
}