{
    "metadata": {
        "video_path": "C:/Users/cesar/OneDrive - Instituto Tecnologico y de Estudios Superiores de Monterrey/Maestr\u00eda/Tesis/Videos/Clips/player5/part2/player5_part2_clip66_grade5.mp4",
        "video_name": "player5_part2_clip66_grade5",
        "player_id": 5,
        "part": 2,
        "clip": 66,
        "grade": 5,
        "duration": 3.036366666666667,
        "fps": 29.97002997002997,
        "frame_width": 1080,
        "frame_height": 1920,
        "total_frames": 91,
        "model": "mobilenet_thin",
        "resize": "0x0",
        "resize_out_ratio": 4.0,
        "reference_point": "Pelvis",
        "keypoints_used": [
            "Pelvis",
            "Right Elbow",
            "Right Wrist"
        ],
        "processing_date": "2025-12-04T05:27:50.731169"
    },
    "Pelvis": [
        [
            504,
            940
        ],
        [
            506,
            948
        ],
        [
            510,
            957
        ],
        [
            510,
            964
        ],
        [
            508,
            966
        ],
        [
            506,
            957
        ],
        [
            508,
            961
        ],
        [
            500,
            999
        ],
        [
            510,
            948
        ],
        [
            508,
            946
        ],
        [
            504,
            946
        ],
        [
            504,
            956
        ],
        [
            506,
            953
        ],
        [
            506,
            952
        ],
        [
            506,
            960
        ],
        [
            506,
            957
        ],
        [
            506,
            960
        ],
        [
            502,
            953
        ],
        [
            502,
            948
        ],
        [
            502,
            949
        ],
        [
            502,
            946
        ],
        [
            498,
            952
        ],
        [
            496,
            948
        ],
        [
            494,
            948
        ],
        [
            496,
            949
        ],
        [
            496,
            952
        ],
        [
            494,
            953
        ],
        [
            494,
            953
        ],
        [
            494,
            952
        ],
        [
            498,
            953
        ],
        [
            498,
            949
        ],
        [
            500,
            949
        ],
        [
            502,
            949
        ],
        [
            504,
            952
        ],
        [
            512,
            946
        ],
        [
            1058,
            368
        ],
        [
            532,
            944
        ],
        [
            536,
            944
        ],
        [
            536,
            946
        ],
        [
            536,
            946
        ],
        [
            536,
            948
        ],
        [
            538,
            952
        ],
        [
            538,
            948
        ],
        [
            542,
            946
        ],
        [
            544,
            940
        ],
        [
            544,
            942
        ],
        [
            544,
            936
        ],
        [
            546,
            936
        ],
        [
            548,
            940
        ],
        [
            546,
            942
        ],
        [
            546,
            944
        ],
        [
            548,
            946
        ],
        [
            550,
            948
        ],
        [
            552,
            944
        ],
        [
            552,
            944
        ],
        [
            556,
            932
        ],
        [
            556,
            938
        ],
        [
            554,
            940
        ],
        [
            554,
            946
        ],
        [
            552,
            946
        ],
        [
            550,
            946
        ],
        [
            548,
            946
        ],
        [
            546,
            938
        ]
    ],
    "Mano Derecha Original": [
        [
            446,
            1104
        ],
        [
            452,
            1112
        ],
        [
            450,
            1118
        ],
        [
            474,
            1110
        ],
        [
            446,
            1132
        ],
        [
            450,
            1130
        ],
        [
            446,
            1132
        ],
        [
            452,
            1116
        ],
        [
            452,
            1050
        ],
        [
            458,
            1104
        ],
        [
            458,
            1106
        ],
        [
            458,
            1106
        ],
        [
            458,
            1104
        ],
        [
            464,
            1052
        ],
        [
            462,
            1108
        ],
        [
            460,
            1112
        ],
        [
            472,
            1050
        ],
        [
            474,
            1050
        ],
        [
            466,
            1104
        ],
        [
            466,
            1104
        ],
        [
            470,
            1098
        ],
        [
            474,
            1092
        ],
        [
            480,
            1086
        ],
        [
            460,
            1062
        ],
        [
            444,
            1059
        ],
        [
            430,
            1050
        ],
        [
            430,
            1032
        ],
        [
            444,
            1008
        ],
        [
            472,
            980
        ],
        [
            508,
            968
        ],
        [
            540,
            964
        ],
        [
            560,
            974
        ],
        [
            574,
            982
        ],
        [
            578,
            991
        ],
        [
            576,
            991
        ],
        [
            1062,
            386
        ],
        [
            570,
            966
        ],
        [
            562,
            960
        ],
        [
            554,
            957
        ],
        [
            550,
            953
        ],
        [
            544,
            953
        ],
        [
            538,
            953
        ],
        [
            536,
            956
        ],
        [
            534,
            956
        ],
        [
            536,
            956
        ],
        [
            538,
            957
        ],
        [
            538,
            960
        ],
        [
            540,
            961
        ],
        [
            542,
            964
        ],
        [
            542,
            966
        ],
        [
            546,
            968
        ],
        [
            550,
            969
        ],
        [
            550,
            969
        ],
        [
            550,
            968
        ],
        [
            552,
            964
        ],
        [
            546,
            956
        ],
        [
            546,
            956
        ],
        [
            544,
            960
        ],
        [
            544,
            961
        ],
        [
            542,
            961
        ],
        [
            540,
            964
        ],
        [
            538,
            964
        ],
        [
            536,
            961
        ]
    ],
    "Mano Derecha Referencia": [
        [
            -58,
            164
        ],
        [
            -54,
            164
        ],
        [
            -60,
            161
        ],
        [
            -36,
            146
        ],
        [
            -62,
            166
        ],
        [
            -56,
            173
        ],
        [
            -62,
            171
        ],
        [
            -48,
            117
        ],
        [
            -58,
            102
        ],
        [
            -50,
            158
        ],
        [
            -46,
            160
        ],
        [
            -46,
            150
        ],
        [
            -48,
            151
        ],
        [
            -42,
            100
        ],
        [
            -44,
            148
        ],
        [
            -46,
            155
        ],
        [
            -34,
            90
        ],
        [
            -28,
            97
        ],
        [
            -36,
            156
        ],
        [
            -36,
            155
        ],
        [
            -32,
            152
        ],
        [
            -24,
            140
        ],
        [
            -16,
            138
        ],
        [
            -34,
            114
        ],
        [
            -52,
            110
        ],
        [
            -66,
            98
        ],
        [
            -64,
            79
        ],
        [
            -50,
            55
        ],
        [
            -22,
            28
        ],
        [
            10,
            15
        ],
        [
            42,
            15
        ],
        [
            60,
            25
        ],
        [
            72,
            33
        ],
        [
            74,
            39
        ],
        [
            64,
            45
        ],
        [
            4,
            18
        ],
        [
            38,
            22
        ],
        [
            26,
            16
        ],
        [
            18,
            11
        ],
        [
            14,
            7
        ],
        [
            8,
            5
        ],
        [
            0,
            1
        ],
        [
            -2,
            8
        ],
        [
            -8,
            10
        ],
        [
            -8,
            16
        ],
        [
            -6,
            15
        ],
        [
            -6,
            24
        ],
        [
            -6,
            25
        ],
        [
            -6,
            24
        ],
        [
            -4,
            24
        ],
        [
            0,
            24
        ],
        [
            2,
            23
        ],
        [
            0,
            21
        ],
        [
            -2,
            24
        ],
        [
            0,
            20
        ],
        [
            -10,
            24
        ],
        [
            -10,
            18
        ],
        [
            -10,
            20
        ],
        [
            -10,
            15
        ],
        [
            -10,
            15
        ],
        [
            -10,
            18
        ],
        [
            -10,
            18
        ],
        [
            -10,
            23
        ]
    ],
    "Codo Derecha Original": [
        [
            478,
            1089
        ],
        [
            478,
            1096
        ],
        [
            476,
            1102
        ],
        [
            480,
            1106
        ],
        [
            478,
            1106
        ],
        [
            478,
            1106
        ],
        [
            484,
            1100
        ],
        [
            478,
            1089
        ],
        [
            480,
            1026
        ],
        [
            476,
            1084
        ],
        [
            474,
            1086
        ],
        [
            476,
            1084
        ],
        [
            476,
            1084
        ],
        [
            486,
            1028
        ],
        [
            478,
            1089
        ],
        [
            482,
            1089
        ],
        [
            490,
            1029
        ],
        [
            492,
            1032
        ],
        [
            494,
            1059
        ],
        [
            494,
            1066
        ],
        [
            492,
            1066
        ],
        [
            494,
            1062
        ],
        [
            494,
            1058
        ],
        [
            472,
            1044
        ],
        [
            470,
            1038
        ],
        [
            464,
            1034
        ],
        [
            468,
            1028
        ],
        [
            474,
            1021
        ],
        [
            482,
            1010
        ],
        [
            492,
            996
        ],
        [
            508,
            988
        ],
        [
            528,
            983
        ],
        [
            538,
            982
        ],
        [
            548,
            983
        ],
        [
            556,
            983
        ],
        [
            1056,
            387
        ],
        [
            540,
            969
        ],
        [
            530,
            974
        ],
        [
            522,
            978
        ],
        [
            518,
            982
        ],
        [
            514,
            982
        ],
        [
            510,
            986
        ],
        [
            508,
            986
        ],
        [
            508,
            988
        ],
        [
            508,
            986
        ],
        [
            508,
            982
        ],
        [
            510,
            980
        ],
        [
            512,
            982
        ],
        [
            516,
            983
        ],
        [
            518,
            986
        ],
        [
            522,
            990
        ],
        [
            522,
            994
        ],
        [
            522,
            996
        ],
        [
            522,
            996
        ],
        [
            522,
            990
        ],
        [
            520,
            988
        ],
        [
            522,
            988
        ],
        [
            520,
            990
        ],
        [
            520,
            990
        ],
        [
            518,
            991
        ],
        [
            516,
            991
        ],
        [
            514,
            991
        ],
        [
            512,
            988
        ]
    ],
    "Codo Derecha Referencia": [
        [
            -26,
            149
        ],
        [
            -28,
            148
        ],
        [
            -34,
            145
        ],
        [
            -30,
            142
        ],
        [
            -30,
            140
        ],
        [
            -28,
            149
        ],
        [
            -24,
            139
        ],
        [
            -22,
            90
        ],
        [
            -30,
            78
        ],
        [
            -32,
            138
        ],
        [
            -30,
            140
        ],
        [
            -28,
            128
        ],
        [
            -30,
            131
        ],
        [
            -20,
            76
        ],
        [
            -28,
            129
        ],
        [
            -24,
            132
        ],
        [
            -16,
            69
        ],
        [
            -10,
            79
        ],
        [
            -8,
            111
        ],
        [
            -8,
            117
        ],
        [
            -10,
            120
        ],
        [
            -4,
            110
        ],
        [
            -2,
            110
        ],
        [
            -22,
            96
        ],
        [
            -26,
            89
        ],
        [
            -32,
            82
        ],
        [
            -26,
            75
        ],
        [
            -20,
            68
        ],
        [
            -12,
            58
        ],
        [
            -6,
            43
        ],
        [
            10,
            39
        ],
        [
            28,
            34
        ],
        [
            36,
            33
        ],
        [
            44,
            31
        ],
        [
            44,
            37
        ],
        [
            -2,
            19
        ],
        [
            8,
            25
        ],
        [
            -6,
            30
        ],
        [
            -14,
            32
        ],
        [
            -18,
            36
        ],
        [
            -22,
            34
        ],
        [
            -28,
            34
        ],
        [
            -30,
            38
        ],
        [
            -34,
            42
        ],
        [
            -36,
            46
        ],
        [
            -36,
            40
        ],
        [
            -34,
            44
        ],
        [
            -34,
            46
        ],
        [
            -32,
            43
        ],
        [
            -28,
            44
        ],
        [
            -24,
            46
        ],
        [
            -26,
            48
        ],
        [
            -28,
            48
        ],
        [
            -30,
            52
        ],
        [
            -30,
            46
        ],
        [
            -36,
            56
        ],
        [
            -34,
            50
        ],
        [
            -34,
            50
        ],
        [
            -34,
            44
        ],
        [
            -34,
            45
        ],
        [
            -34,
            45
        ],
        [
            -34,
            45
        ],
        [
            -34,
            50
        ]
    ],
    "timestamps": [
        0.20020000000000002,
        0.23356666666666667,
        0.26693333333333336,
        0.33366666666666667,
        0.3670333333333334,
        0.40040000000000003,
        0.4337666666666667,
        0.5672333333333334,
        0.6006,
        0.6339666666666667,
        0.6673333333333333,
        0.7007000000000001,
        0.7340666666666668,
        0.8008000000000001,
        0.8341666666666667,
        0.8675333333333334,
        0.9342666666666667,
        1.0343666666666667,
        1.0677333333333334,
        1.1011,
        1.2012,
        1.2679333333333334,
        1.3013000000000001,
        1.5015,
        1.5348666666666668,
        1.5682333333333334,
        1.6016000000000001,
        1.6349666666666667,
        1.6683333333333334,
        1.7017,
        1.7350666666666668,
        1.7684333333333335,
        1.8018000000000003,
        1.8351666666666668,
        1.9019000000000001,
        2.0020000000000002,
        2.0687333333333333,
        2.1021,
        2.135466666666667,
        2.1688333333333336,
        2.2022,
        2.2355666666666667,
        2.2689333333333335,
        2.3023000000000002,
        2.3356666666666666,
        2.3690333333333333,
        2.4024,
        2.435766666666667,
        2.4691333333333336,
        2.5025,
        2.5358666666666667,
        2.5692333333333335,
        2.6026000000000002,
        2.635966666666667,
        2.6693333333333333,
        2.7694333333333336,
        2.8028000000000004,
        2.8361666666666667,
        2.8695333333333335,
        2.9029000000000003,
        2.936266666666667,
        2.9696333333333333,
        3.003
    ],
    "total_coordinates": 63
}