{
    "metadata": {
        "video_path": "Videos/Clips/player4/part1/player4_part1_clip33_grade6.mp4",
        "video_name": "player4_part1_clip33_grade6",
        "player_id": 4,
        "part": 1,
        "clip": 33,
        "grade": 6,
        "duration": 3.036366666666667,
        "fps": 29.97002997002997,
        "frame_width": 720,
        "frame_height": 1280,
        "total_frames": 91,
        "model": "mobilenet_thin",
        "resize": "0x0",
        "resize_out_ratio": 4.0,
        "reference_point": "Pelvis",
        "keypoints_used": [
            "Pelvis",
            "Left Shoulder",
            "Right Elbow",
            "Right Wrist"
        ],
        "interpolation_method": "linear",
        "interpolated_frames": 45,
        "processing_date": "2026-03-02T01:05:29.849933"
    },
    "Pelvis": [
        [
            408,
            598
        ],
        [
            408,
            598
        ],
        [
            410,
            598
        ],
        [
            410,
            598
        ],
        [
            410,
            598
        ],
        [
            410,
            598
        ],
        [
            410,
            594
        ],
        [
            412,
            592
        ],
        [
            413,
            590
        ],
        [
            413,
            590
        ],
        [
            415,
            588
        ],
        [
            420,
            590
        ],
        [
            426,
            592
        ],
        [
            428,
            594
        ],
        [
            432,
            596
        ],
        [
            434,
            592
        ],
        [
            437,
            596
        ],
        [
            442,
            600
        ],
        [
            444,
            604
        ],
        [
            446,
            604
        ],
        [
            448,
            604
        ],
        [
            452,
            600
        ],
        [
            462,
            602
        ],
        [
            464,
            602
        ],
        [
            462,
            598
        ],
        [
            464,
            598
        ],
        [
            462,
            602
        ],
        [
            462,
            602
        ],
        [
            459,
            606
        ],
        [
            459,
            608
        ],
        [
            459,
            608
        ],
        [
            458,
            608
        ],
        [
            459,
            610
        ],
        [
            458,
            610
        ],
        [
            456,
            610
        ],
        [
            454,
            612
        ],
        [
            450,
            612
        ],
        [
            446,
            612
        ],
        [
            446,
            608
        ],
        [
            442,
            606
        ],
        [
            444,
            602
        ],
        [
            440,
            600
        ],
        [
            440,
            600
        ],
        [
            437,
            600
        ],
        [
            437,
            600
        ],
        [
            434,
            600
        ],
        [
            430,
            600
        ],
        [
            428,
            600
        ],
        [
            428,
            598
        ],
        [
            426,
            598
        ],
        [
            422,
            598
        ],
        [
            424,
            600
        ],
        [
            422,
            600
        ],
        [
            413,
            600
        ],
        [
            410,
            604
        ],
        [
            408,
            604
        ],
        [
            408,
            604
        ],
        [
            408,
            606
        ],
        [
            404,
            610
        ],
        [
            404,
            610
        ],
        [
            402,
            614
        ],
        [
            400,
            614
        ],
        [
            398,
            616
        ],
        [
            396,
            614
        ],
        [
            394,
            614
        ],
        [
            394,
            614
        ],
        [
            390,
            610
        ],
        [
            390,
            608
        ],
        [
            388,
            608
        ],
        [
            388,
            606
        ],
        [
            386,
            604
        ],
        [
            386,
            602
        ],
        [
            386,
            604
        ],
        [
            384,
            598
        ],
        [
            384,
            602
        ],
        [
            382,
            604
        ],
        [
            380,
            604
        ],
        [
            378,
            600
        ],
        [
            374,
            606
        ],
        [
            374,
            604
        ],
        [
            372,
            606
        ],
        [
            369,
            608
        ],
        [
            368,
            606
        ],
        [
            368,
            604
        ],
        [
            368,
            602
        ],
        [
            366,
            600
        ],
        [
            366,
            600
        ],
        [
            364,
            600
        ],
        [
            362,
            602
        ],
        [
            362,
            604
        ]
    ],
    "Left Shoulder Original": [
        [
            444,
            670
        ],
        [
            444,
            670
        ],
        [
            446,
            670
        ],
        [
            444,
            670
        ],
        [
            444,
            668
        ],
        [
            444,
            666
        ],
        [
            444,
            664
        ],
        [
            446,
            660
        ],
        [
            446,
            658
        ],
        [
            446,
            658
        ],
        [
            448,
            656
        ],
        [
            450,
            658
        ],
        [
            452,
            658
        ],
        [
            450,
            660
        ],
        [
            452,
            664
        ],
        [
            450,
            664
        ],
        [
            448,
            668
        ],
        [
            448,
            668
        ],
        [
            446,
            672
        ],
        [
            446,
            672
        ],
        [
            446,
            672
        ],
        [
            444,
            668
        ],
        [
            440,
            664
        ],
        [
            437,
            660
        ],
        [
            435,
            658
        ],
        [
            435,
            656
        ],
        [
            434,
            658
        ],
        [
            432,
            656
        ],
        [
            432,
            656
        ],
        [
            430,
            656
        ],
        [
            430,
            656
        ],
        [
            428,
            656
        ],
        [
            430,
            658
        ],
        [
            428,
            662
        ],
        [
            430,
            664
        ],
        [
            430,
            664
        ],
        [
            428,
            664
        ],
        [
            426,
            662
        ],
        [
            424,
            660
        ],
        [
            422,
            658
        ],
        [
            420,
            654
        ],
        [
            420,
            652
        ],
        [
            418,
            652
        ],
        [
            413,
            652
        ],
        [
            413,
            652
        ],
        [
            413,
            652
        ],
        [
            413,
            652
        ],
        [
            412,
            652
        ],
        [
            413,
            650
        ],
        [
            412,
            650
        ],
        [
            412,
            650
        ],
        [
            412,
            650
        ],
        [
            412,
            648
        ],
        [
            418,
            648
        ],
        [
            418,
            650
        ],
        [
            415,
            650
        ],
        [
            413,
            652
        ],
        [
            413,
            650
        ],
        [
            412,
            654
        ],
        [
            413,
            654
        ],
        [
            412,
            658
        ],
        [
            413,
            656
        ],
        [
            413,
            660
        ],
        [
            412,
            658
        ],
        [
            412,
            658
        ],
        [
            412,
            658
        ],
        [
            412,
            654
        ],
        [
            410,
            648
        ],
        [
            408,
            646
        ],
        [
            408,
            644
        ],
        [
            406,
            642
        ],
        [
            406,
            640
        ],
        [
            406,
            640
        ],
        [
            406,
            642
        ],
        [
            406,
            642
        ],
        [
            406,
            642
        ],
        [
            402,
            642
        ],
        [
            402,
            644
        ],
        [
            402,
            644
        ],
        [
            402,
            646
        ],
        [
            398,
            648
        ],
        [
            398,
            650
        ],
        [
            396,
            650
        ],
        [
            391,
            650
        ],
        [
            391,
            650
        ],
        [
            390,
            650
        ],
        [
            390,
            648
        ],
        [
            388,
            650
        ],
        [
            388,
            652
        ],
        [
            388,
            656
        ]
    ],
    "Left Shoulder Relative": [
        [
            36,
            72
        ],
        [
            36,
            72
        ],
        [
            36,
            72
        ],
        [
            34,
            72
        ],
        [
            34,
            70
        ],
        [
            34,
            68
        ],
        [
            34,
            70
        ],
        [
            34,
            68
        ],
        [
            33,
            68
        ],
        [
            33,
            68
        ],
        [
            33,
            68
        ],
        [
            30,
            68
        ],
        [
            26,
            66
        ],
        [
            22,
            66
        ],
        [
            20,
            68
        ],
        [
            16,
            72
        ],
        [
            11,
            72
        ],
        [
            6,
            68
        ],
        [
            2,
            68
        ],
        [
            0,
            68
        ],
        [
            -2,
            68
        ],
        [
            -8,
            68
        ],
        [
            -22,
            62
        ],
        [
            -27,
            58
        ],
        [
            -27,
            60
        ],
        [
            -29,
            58
        ],
        [
            -28,
            56
        ],
        [
            -30,
            54
        ],
        [
            -27,
            50
        ],
        [
            -29,
            48
        ],
        [
            -29,
            48
        ],
        [
            -30,
            48
        ],
        [
            -29,
            48
        ],
        [
            -30,
            52
        ],
        [
            -26,
            54
        ],
        [
            -24,
            52
        ],
        [
            -22,
            52
        ],
        [
            -20,
            50
        ],
        [
            -22,
            52
        ],
        [
            -20,
            52
        ],
        [
            -24,
            52
        ],
        [
            -20,
            52
        ],
        [
            -22,
            52
        ],
        [
            -24,
            52
        ],
        [
            -24,
            52
        ],
        [
            -21,
            52
        ],
        [
            -17,
            52
        ],
        [
            -16,
            52
        ],
        [
            -15,
            52
        ],
        [
            -14,
            52
        ],
        [
            -10,
            52
        ],
        [
            -12,
            50
        ],
        [
            -10,
            48
        ],
        [
            5,
            48
        ],
        [
            8,
            46
        ],
        [
            7,
            46
        ],
        [
            5,
            48
        ],
        [
            5,
            44
        ],
        [
            8,
            44
        ],
        [
            9,
            44
        ],
        [
            10,
            44
        ],
        [
            13,
            42
        ],
        [
            15,
            44
        ],
        [
            16,
            44
        ],
        [
            18,
            44
        ],
        [
            18,
            44
        ],
        [
            22,
            44
        ],
        [
            20,
            40
        ],
        [
            20,
            38
        ],
        [
            20,
            38
        ],
        [
            20,
            38
        ],
        [
            20,
            38
        ],
        [
            20,
            36
        ],
        [
            22,
            44
        ],
        [
            22,
            40
        ],
        [
            24,
            38
        ],
        [
            22,
            38
        ],
        [
            24,
            44
        ],
        [
            28,
            38
        ],
        [
            28,
            42
        ],
        [
            26,
            42
        ],
        [
            29,
            42
        ],
        [
            28,
            44
        ],
        [
            23,
            46
        ],
        [
            23,
            48
        ],
        [
            24,
            50
        ],
        [
            24,
            48
        ],
        [
            24,
            50
        ],
        [
            26,
            50
        ],
        [
            26,
            52
        ]
    ],
    "Right Elbow Original": [
        [
            391,
            634
        ],
        [
            388,
            634
        ],
        [
            388,
            634
        ],
        [
            388,
            632
        ],
        [
            388,
            630
        ],
        [
            390,
            630
        ],
        [
            390,
            628
        ],
        [
            394,
            632
        ],
        [
            396,
            634
        ],
        [
            398,
            634
        ],
        [
            400,
            628
        ],
        [
            402,
            626
        ],
        [
            404,
            628
        ],
        [
            410,
            630
        ],
        [
            408,
            632
        ],
        [
            408,
            636
        ],
        [
            412,
            638
        ],
        [
            415,
            638
        ],
        [
            426,
            636
        ],
        [
            428,
            636
        ],
        [
            430,
            636
        ],
        [
            432,
            632
        ],
        [
            442,
            628
        ],
        [
            444,
            626
        ],
        [
            446,
            624
        ],
        [
            446,
            620
        ],
        [
            442,
            624
        ],
        [
            448,
            626
        ],
        [
            446,
            630
        ],
        [
            454,
            634
        ],
        [
            456,
            634
        ],
        [
            456,
            634
        ],
        [
            454,
            636
        ],
        [
            430,
            636
        ],
        [
            429,
            637
        ],
        [
            428,
            638
        ],
        [
            422,
            640
        ],
        [
            415,
            642
        ],
        [
            413,
            640
        ],
        [
            413,
            640
        ],
        [
            408,
            636
        ],
        [
            398,
            642
        ],
        [
            402,
            638
        ],
        [
            405,
            634
        ],
        [
            409,
            630
        ],
        [
            413,
            626
        ],
        [
            416,
            622
        ],
        [
            420,
            618
        ],
        [
            418,
            620
        ],
        [
            415,
            622
        ],
        [
            391,
            660
        ],
        [
            392,
            664
        ],
        [
            394,
            668
        ],
        [
            391,
            670
        ],
        [
            404,
            624
        ],
        [
            402,
            624
        ],
        [
            398,
            626
        ],
        [
            396,
            626
        ],
        [
            390,
            652
        ],
        [
            398,
            632
        ],
        [
            394,
            642
        ],
        [
            374,
            670
        ],
        [
            374,
            666
        ],
        [
            374,
            666
        ],
        [
            374,
            660
        ],
        [
            376,
            648
        ],
        [
            360,
            644
        ],
        [
            366,
            630
        ],
        [
            376,
            630
        ],
        [
            378,
            624
        ],
        [
            378,
            620
        ],
        [
            378,
            618
        ],
        [
            376,
            618
        ],
        [
            376,
            614
        ],
        [
            372,
            618
        ],
        [
            369,
            618
        ],
        [
            368,
            620
        ],
        [
            366,
            622
        ],
        [
            362,
            624
        ],
        [
            362,
            622
        ],
        [
            358,
            626
        ],
        [
            358,
            626
        ],
        [
            356,
            624
        ],
        [
            354,
            628
        ],
        [
            354,
            624
        ],
        [
            352,
            624
        ],
        [
            354,
            622
        ],
        [
            348,
            626
        ],
        [
            346,
            628
        ],
        [
            346,
            626
        ]
    ],
    "Right Elbow Relative": [
        [
            -17,
            36
        ],
        [
            -20,
            36
        ],
        [
            -22,
            36
        ],
        [
            -22,
            34
        ],
        [
            -22,
            32
        ],
        [
            -20,
            32
        ],
        [
            -20,
            34
        ],
        [
            -18,
            40
        ],
        [
            -17,
            44
        ],
        [
            -15,
            44
        ],
        [
            -15,
            40
        ],
        [
            -18,
            36
        ],
        [
            -22,
            36
        ],
        [
            -18,
            36
        ],
        [
            -24,
            36
        ],
        [
            -26,
            44
        ],
        [
            -25,
            42
        ],
        [
            -27,
            38
        ],
        [
            -18,
            32
        ],
        [
            -18,
            32
        ],
        [
            -18,
            32
        ],
        [
            -20,
            32
        ],
        [
            -20,
            26
        ],
        [
            -20,
            24
        ],
        [
            -16,
            26
        ],
        [
            -18,
            22
        ],
        [
            -20,
            22
        ],
        [
            -14,
            24
        ],
        [
            -13,
            24
        ],
        [
            -5,
            26
        ],
        [
            -3,
            26
        ],
        [
            -2,
            26
        ],
        [
            -5,
            26
        ],
        [
            -28,
            26
        ],
        [
            -27,
            27
        ],
        [
            -26,
            26
        ],
        [
            -28,
            28
        ],
        [
            -31,
            30
        ],
        [
            -33,
            32
        ],
        [
            -29,
            34
        ],
        [
            -36,
            34
        ],
        [
            -42,
            42
        ],
        [
            -38,
            38
        ],
        [
            -32,
            34
        ],
        [
            -28,
            30
        ],
        [
            -21,
            26
        ],
        [
            -14,
            22
        ],
        [
            -8,
            18
        ],
        [
            -10,
            22
        ],
        [
            -11,
            24
        ],
        [
            -31,
            62
        ],
        [
            -32,
            64
        ],
        [
            -28,
            68
        ],
        [
            -22,
            70
        ],
        [
            -6,
            20
        ],
        [
            -6,
            20
        ],
        [
            -10,
            22
        ],
        [
            -12,
            20
        ],
        [
            -14,
            42
        ],
        [
            -6,
            22
        ],
        [
            -8,
            28
        ],
        [
            -26,
            56
        ],
        [
            -24,
            50
        ],
        [
            -22,
            52
        ],
        [
            -20,
            46
        ],
        [
            -18,
            34
        ],
        [
            -30,
            34
        ],
        [
            -24,
            22
        ],
        [
            -12,
            22
        ],
        [
            -10,
            18
        ],
        [
            -8,
            16
        ],
        [
            -8,
            16
        ],
        [
            -10,
            14
        ],
        [
            -8,
            16
        ],
        [
            -12,
            16
        ],
        [
            -13,
            14
        ],
        [
            -12,
            16
        ],
        [
            -12,
            22
        ],
        [
            -12,
            18
        ],
        [
            -12,
            18
        ],
        [
            -14,
            20
        ],
        [
            -11,
            18
        ],
        [
            -12,
            18
        ],
        [
            -14,
            24
        ],
        [
            -14,
            22
        ],
        [
            -14,
            24
        ],
        [
            -12,
            22
        ],
        [
            -16,
            26
        ],
        [
            -16,
            26
        ],
        [
            -16,
            22
        ]
    ],
    "Right Wrist Original": [
        [
            404,
            646
        ],
        [
            400,
            642
        ],
        [
            396,
            640
        ],
        [
            396,
            642
        ],
        [
            396,
            640
        ],
        [
            396,
            640
        ],
        [
            396,
            640
        ],
        [
            396,
            652
        ],
        [
            398,
            636
        ],
        [
            398,
            636
        ],
        [
            399,
            633
        ],
        [
            400,
            630
        ],
        [
            402,
            628
        ],
        [
            406,
            630
        ],
        [
            407,
            631
        ],
        [
            409,
            632
        ],
        [
            410,
            634
        ],
        [
            412,
            635
        ],
        [
            413,
            636
        ],
        [
            413,
            636
        ],
        [
            418,
            638
        ],
        [
            418,
            636
        ],
        [
            418,
            634
        ],
        [
            414,
            635
        ],
        [
            410,
            637
        ],
        [
            406,
            638
        ],
        [
            405,
            640
        ],
        [
            404,
            642
        ],
        [
            404,
            643
        ],
        [
            403,
            645
        ],
        [
            402,
            647
        ],
        [
            401,
            649
        ],
        [
            400,
            651
        ],
        [
            400,
            652
        ],
        [
            399,
            654
        ],
        [
            398,
            656
        ],
        [
            396,
            656
        ],
        [
            393,
            656
        ],
        [
            391,
            656
        ],
        [
            389,
            656
        ],
        [
            386,
            656
        ],
        [
            384,
            656
        ],
        [
            384,
            658
        ],
        [
            384,
            660
        ],
        [
            385,
            662
        ],
        [
            385,
            664
        ],
        [
            385,
            666
        ],
        [
            385,
            668
        ],
        [
            385,
            670
        ],
        [
            385,
            672
        ],
        [
            386,
            674
        ],
        [
            386,
            676
        ],
        [
            386,
            678
        ],
        [
            386,
            682
        ],
        [
            392,
            658
        ],
        [
            398,
            634
        ],
        [
            396,
            642
        ],
        [
            391,
            648
        ],
        [
            390,
            658
        ],
        [
            400,
            650
        ],
        [
            386,
            667
        ],
        [
            372,
            684
        ],
        [
            366,
            680
        ],
        [
            358,
            682
        ],
        [
            374,
            664
        ],
        [
            376,
            656
        ],
        [
            375,
            648
        ],
        [
            374,
            640
        ],
        [
            376,
            616
        ],
        [
            382,
            608
        ],
        [
            388,
            604
        ],
        [
            386,
            602
        ],
        [
            386,
            600
        ],
        [
            386,
            596
        ],
        [
            382,
            596
        ],
        [
            376,
            598
        ],
        [
            374,
            598
        ],
        [
            369,
            598
        ],
        [
            366,
            606
        ],
        [
            364,
            606
        ],
        [
            360,
            608
        ],
        [
            358,
            612
        ],
        [
            358,
            612
        ],
        [
            356,
            612
        ],
        [
            354,
            616
        ],
        [
            354,
            618
        ],
        [
            354,
            620
        ],
        [
            354,
            624
        ],
        [
            354,
            624
        ],
        [
            360,
            626
        ]
    ],
    "Right Wrist Relative": [
        [
            -4,
            48
        ],
        [
            -8,
            44
        ],
        [
            -14,
            42
        ],
        [
            -14,
            44
        ],
        [
            -14,
            42
        ],
        [
            -14,
            42
        ],
        [
            -14,
            46
        ],
        [
            -16,
            60
        ],
        [
            -15,
            46
        ],
        [
            -15,
            46
        ],
        [
            -16,
            45
        ],
        [
            -20,
            40
        ],
        [
            -24,
            36
        ],
        [
            -22,
            36
        ],
        [
            -25,
            35
        ],
        [
            -25,
            40
        ],
        [
            -27,
            38
        ],
        [
            -30,
            35
        ],
        [
            -31,
            32
        ],
        [
            -33,
            32
        ],
        [
            -30,
            34
        ],
        [
            -34,
            36
        ],
        [
            -44,
            32
        ],
        [
            -50,
            33
        ],
        [
            -52,
            39
        ],
        [
            -58,
            40
        ],
        [
            -57,
            38
        ],
        [
            -58,
            40
        ],
        [
            -55,
            37
        ],
        [
            -56,
            37
        ],
        [
            -57,
            39
        ],
        [
            -57,
            41
        ],
        [
            -59,
            41
        ],
        [
            -58,
            42
        ],
        [
            -57,
            44
        ],
        [
            -56,
            44
        ],
        [
            -54,
            44
        ],
        [
            -53,
            44
        ],
        [
            -55,
            48
        ],
        [
            -53,
            50
        ],
        [
            -58,
            54
        ],
        [
            -56,
            56
        ],
        [
            -56,
            58
        ],
        [
            -53,
            60
        ],
        [
            -52,
            62
        ],
        [
            -49,
            64
        ],
        [
            -45,
            66
        ],
        [
            -43,
            68
        ],
        [
            -43,
            72
        ],
        [
            -41,
            74
        ],
        [
            -36,
            76
        ],
        [
            -38,
            76
        ],
        [
            -36,
            78
        ],
        [
            -27,
            82
        ],
        [
            -18,
            54
        ],
        [
            -10,
            30
        ],
        [
            -12,
            38
        ],
        [
            -17,
            42
        ],
        [
            -14,
            48
        ],
        [
            -4,
            40
        ],
        [
            -16,
            53
        ],
        [
            -28,
            70
        ],
        [
            -32,
            64
        ],
        [
            -38,
            68
        ],
        [
            -20,
            50
        ],
        [
            -18,
            42
        ],
        [
            -15,
            38
        ],
        [
            -16,
            32
        ],
        [
            -12,
            8
        ],
        [
            -6,
            2
        ],
        [
            2,
            0
        ],
        [
            0,
            0
        ],
        [
            0,
            -4
        ],
        [
            2,
            -2
        ],
        [
            -2,
            -6
        ],
        [
            -6,
            -6
        ],
        [
            -6,
            -6
        ],
        [
            -9,
            -2
        ],
        [
            -8,
            0
        ],
        [
            -10,
            2
        ],
        [
            -12,
            2
        ],
        [
            -11,
            4
        ],
        [
            -10,
            6
        ],
        [
            -12,
            8
        ],
        [
            -14,
            14
        ],
        [
            -12,
            18
        ],
        [
            -12,
            20
        ],
        [
            -10,
            24
        ],
        [
            -8,
            22
        ],
        [
            -2,
            22
        ]
    ],
    "timestamps": [
        0.03336666666666667,
        0.06673333333333334,
        0.10010000000000001,
        0.13346666666666668,
        0.16683333333333333,
        0.20020000000000002,
        0.23356666666666667,
        0.26693333333333336,
        0.3003,
        0.33366666666666667,
        0.3670333333333334,
        0.40040000000000003,
        0.4337666666666667,
        0.46713333333333334,
        0.5005000000000001,
        0.5338666666666667,
        0.5672333333333334,
        0.6006,
        0.6339666666666667,
        0.6673333333333333,
        0.7007000000000001,
        0.7340666666666668,
        0.7674333333333334,
        0.8008000000000001,
        0.8341666666666667,
        0.8675333333333334,
        0.9009000000000001,
        0.9342666666666667,
        0.9676333333333333,
        1.0010000000000001,
        1.0343666666666667,
        1.0677333333333334,
        1.1011,
        1.1344666666666667,
        1.1678333333333333,
        1.2012,
        1.2345666666666668,
        1.2679333333333334,
        1.3013000000000001,
        1.3346666666666667,
        1.3680333333333334,
        1.4014000000000002,
        1.4347666666666667,
        1.4681333333333335,
        1.5015,
        1.5348666666666668,
        1.5682333333333334,
        1.6016000000000001,
        1.6349666666666667,
        1.6683333333333334,
        1.7017,
        1.7350666666666668,
        1.7684333333333335,
        1.8018000000000003,
        1.8351666666666668,
        1.8685333333333334,
        1.9019000000000001,
        1.9352666666666667,
        1.9686333333333335,
        2.0020000000000002,
        2.0353666666666665,
        2.0687333333333333,
        2.1021,
        2.135466666666667,
        2.1688333333333336,
        2.2022,
        2.2355666666666667,
        2.2689333333333335,
        2.3023000000000002,
        2.3356666666666666,
        2.3690333333333333,
        2.4024,
        2.435766666666667,
        2.4691333333333336,
        2.5025,
        2.5358666666666667,
        2.5692333333333335,
        2.6026000000000002,
        2.635966666666667,
        2.6693333333333333,
        2.7027,
        2.736066666666667,
        2.7694333333333336,
        2.8028000000000004,
        2.8361666666666667,
        2.8695333333333335,
        2.9029000000000003,
        2.936266666666667,
        2.9696333333333333,
        3.003
    ],
    "total_coordinates": 90
}