{
    "metadata": {
        "video_path": "Videos/Clips/player10/part1/player10_part1_clip29_grade8.mp4",
        "video_name": "player10_part1_clip29_grade8",
        "player_id": 10,
        "part": 1,
        "clip": 29,
        "grade": 8,
        "duration": 3.0,
        "fps": 30.0,
        "frame_width": 1080,
        "frame_height": 1920,
        "total_frames": 90,
        "model": "mobilenet_thin",
        "resize": "0x0",
        "resize_out_ratio": 4.0,
        "reference_point": "Pelvis",
        "keypoints_used": [
            "Pelvis",
            "Right Elbow",
            "Right Wrist"
        ],
        "processing_date": "2025-11-10T20:10:44.244131"
    },
    "Pelvis": [
        [
            574,
            960
        ],
        [
            586,
            961
        ],
        [
            594,
            942
        ],
        [
            578,
            952
        ],
        [
            592,
            948
        ],
        [
            586,
            949
        ],
        [
            602,
            946
        ],
        [
            588,
            938
        ],
        [
            590,
            934
        ],
        [
            596,
            936
        ],
        [
            592,
            932
        ],
        [
            598,
            932
        ],
        [
            610,
            930
        ],
        [
            612,
            927
        ],
        [
            616,
            927
        ],
        [
            618,
            934
        ],
        [
            623,
            940
        ],
        [
            626,
            934
        ],
        [
            630,
            934
        ],
        [
            632,
            930
        ],
        [
            636,
            932
        ],
        [
            640,
            930
        ],
        [
            644,
            927
        ],
        [
            650,
            926
        ],
        [
            654,
            927
        ],
        [
            658,
            932
        ],
        [
            664,
            932
        ],
        [
            666,
            938
        ],
        [
            672,
            940
        ],
        [
            682,
            934
        ],
        [
            686,
            934
        ],
        [
            690,
            938
        ],
        [
            688,
            940
        ],
        [
            694,
            930
        ],
        [
            696,
            922
        ],
        [
            696,
            919
        ],
        [
            696,
            918
        ],
        [
            698,
            918
        ],
        [
            696,
            918
        ],
        [
            696,
            923
        ],
        [
            696,
            927
        ],
        [
            696,
            923
        ],
        [
            698,
            932
        ],
        [
            700,
            927
        ],
        [
            700,
            927
        ],
        [
            700,
            926
        ],
        [
            700,
            918
        ],
        [
            702,
            918
        ],
        [
            698,
            923
        ],
        [
            696,
            926
        ],
        [
            692,
            944
        ],
        [
            692,
            936
        ],
        [
            688,
            936
        ],
        [
            686,
            934
        ],
        [
            684,
            932
        ],
        [
            680,
            926
        ],
        [
            678,
            922
        ],
        [
            674,
            919
        ],
        [
            672,
            919
        ],
        [
            670,
            919
        ]
    ],
    "Mano Derecha Original": [
        [
            514,
            1032
        ],
        [
            520,
            1028
        ],
        [
            520,
            1042
        ],
        [
            520,
            1042
        ],
        [
            524,
            1040
        ],
        [
            528,
            1048
        ],
        [
            528,
            1050
        ],
        [
            534,
            1054
        ],
        [
            534,
            1056
        ],
        [
            534,
            1058
        ],
        [
            536,
            1062
        ],
        [
            542,
            1066
        ],
        [
            586,
            1008
        ],
        [
            582,
            1021
        ],
        [
            574,
            1028
        ],
        [
            570,
            1029
        ],
        [
            656,
            986
        ],
        [
            678,
            961
        ],
        [
            672,
            957
        ],
        [
            696,
            953
        ],
        [
            714,
            956
        ],
        [
            722,
            953
        ],
        [
            724,
            953
        ],
        [
            710,
            953
        ],
        [
            710,
            952
        ],
        [
            708,
            952
        ],
        [
            714,
            949
        ],
        [
            706,
            946
        ],
        [
            698,
            940
        ],
        [
            698,
            942
        ],
        [
            696,
            940
        ],
        [
            692,
            942
        ],
        [
            692,
            940
        ],
        [
            710,
            930
        ],
        [
            712,
            930
        ],
        [
            704,
            940
        ],
        [
            712,
            942
        ],
        [
            716,
            946
        ],
        [
            714,
            952
        ],
        [
            720,
            956
        ],
        [
            714,
            961
        ],
        [
            720,
            961
        ],
        [
            712,
            961
        ],
        [
            716,
            956
        ],
        [
            706,
            952
        ],
        [
            700,
            952
        ],
        [
            698,
            948
        ],
        [
            692,
            949
        ],
        [
            688,
            952
        ],
        [
            682,
            953
        ],
        [
            678,
            957
        ],
        [
            674,
            957
        ],
        [
            672,
            960
        ],
        [
            670,
            957
        ],
        [
            666,
            957
        ],
        [
            664,
            949
        ],
        [
            658,
            946
        ],
        [
            654,
            944
        ],
        [
            652,
            948
        ],
        [
            646,
            953
        ]
    ],
    "Mano Derecha Referencia": [
        [
            -60,
            72
        ],
        [
            -66,
            67
        ],
        [
            -74,
            100
        ],
        [
            -58,
            90
        ],
        [
            -68,
            92
        ],
        [
            -58,
            99
        ],
        [
            -74,
            104
        ],
        [
            -54,
            116
        ],
        [
            -56,
            122
        ],
        [
            -62,
            122
        ],
        [
            -56,
            130
        ],
        [
            -56,
            134
        ],
        [
            -24,
            78
        ],
        [
            -30,
            94
        ],
        [
            -42,
            101
        ],
        [
            -48,
            95
        ],
        [
            33,
            46
        ],
        [
            52,
            27
        ],
        [
            42,
            23
        ],
        [
            64,
            23
        ],
        [
            78,
            24
        ],
        [
            82,
            23
        ],
        [
            80,
            26
        ],
        [
            60,
            27
        ],
        [
            56,
            25
        ],
        [
            50,
            20
        ],
        [
            50,
            17
        ],
        [
            40,
            8
        ],
        [
            26,
            0
        ],
        [
            16,
            8
        ],
        [
            10,
            6
        ],
        [
            2,
            4
        ],
        [
            4,
            0
        ],
        [
            16,
            0
        ],
        [
            16,
            8
        ],
        [
            8,
            21
        ],
        [
            16,
            24
        ],
        [
            18,
            28
        ],
        [
            18,
            34
        ],
        [
            24,
            33
        ],
        [
            18,
            34
        ],
        [
            24,
            38
        ],
        [
            14,
            29
        ],
        [
            16,
            29
        ],
        [
            6,
            25
        ],
        [
            0,
            26
        ],
        [
            -2,
            30
        ],
        [
            -10,
            31
        ],
        [
            -10,
            29
        ],
        [
            -14,
            27
        ],
        [
            -14,
            13
        ],
        [
            -18,
            21
        ],
        [
            -16,
            24
        ],
        [
            -16,
            23
        ],
        [
            -18,
            25
        ],
        [
            -16,
            23
        ],
        [
            -20,
            24
        ],
        [
            -20,
            25
        ],
        [
            -20,
            29
        ],
        [
            -24,
            34
        ]
    ],
    "Codo Derecha Original": [
        [
            524,
            1028
        ],
        [
            532,
            1028
        ],
        [
            530,
            1040
        ],
        [
            532,
            1032
        ],
        [
            538,
            1036
        ],
        [
            546,
            1036
        ],
        [
            542,
            1038
        ],
        [
            546,
            1042
        ],
        [
            550,
            1044
        ],
        [
            558,
            1046
        ],
        [
            556,
            1050
        ],
        [
            564,
            1050
        ],
        [
            590,
            999
        ],
        [
            584,
            1016
        ],
        [
            582,
            1018
        ],
        [
            590,
            1020
        ],
        [
            626,
            991
        ],
        [
            628,
            968
        ],
        [
            636,
            976
        ],
        [
            658,
            969
        ],
        [
            676,
            964
        ],
        [
            688,
            960
        ],
        [
            688,
            960
        ],
        [
            686,
            957
        ],
        [
            688,
            956
        ],
        [
            664,
            960
        ],
        [
            686,
            956
        ],
        [
            666,
            968
        ],
        [
            668,
            968
        ],
        [
            668,
            960
        ],
        [
            666,
            966
        ],
        [
            664,
            964
        ],
        [
            664,
            966
        ],
        [
            670,
            961
        ],
        [
            670,
            956
        ],
        [
            672,
            960
        ],
        [
            674,
            960
        ],
        [
            676,
            964
        ],
        [
            678,
            966
        ],
        [
            678,
            969
        ],
        [
            678,
            976
        ],
        [
            680,
            978
        ],
        [
            678,
            978
        ],
        [
            676,
            978
        ],
        [
            676,
            974
        ],
        [
            676,
            969
        ],
        [
            672,
            968
        ],
        [
            670,
            972
        ],
        [
            668,
            978
        ],
        [
            668,
            978
        ],
        [
            666,
            982
        ],
        [
            664,
            982
        ],
        [
            662,
            983
        ],
        [
            658,
            986
        ],
        [
            656,
            982
        ],
        [
            654,
            978
        ],
        [
            652,
            976
        ],
        [
            650,
            972
        ],
        [
            648,
            972
        ],
        [
            644,
            978
        ]
    ],
    "Codo Derecha Referencia": [
        [
            -50,
            68
        ],
        [
            -54,
            67
        ],
        [
            -64,
            98
        ],
        [
            -46,
            80
        ],
        [
            -54,
            88
        ],
        [
            -40,
            87
        ],
        [
            -60,
            92
        ],
        [
            -42,
            104
        ],
        [
            -40,
            110
        ],
        [
            -38,
            110
        ],
        [
            -36,
            118
        ],
        [
            -34,
            118
        ],
        [
            -20,
            69
        ],
        [
            -28,
            89
        ],
        [
            -34,
            91
        ],
        [
            -28,
            86
        ],
        [
            3,
            51
        ],
        [
            2,
            34
        ],
        [
            6,
            42
        ],
        [
            26,
            39
        ],
        [
            40,
            32
        ],
        [
            48,
            30
        ],
        [
            44,
            33
        ],
        [
            36,
            31
        ],
        [
            34,
            29
        ],
        [
            6,
            28
        ],
        [
            22,
            24
        ],
        [
            0,
            30
        ],
        [
            -4,
            28
        ],
        [
            -14,
            26
        ],
        [
            -20,
            32
        ],
        [
            -26,
            26
        ],
        [
            -24,
            26
        ],
        [
            -24,
            31
        ],
        [
            -26,
            34
        ],
        [
            -24,
            41
        ],
        [
            -22,
            42
        ],
        [
            -22,
            46
        ],
        [
            -18,
            48
        ],
        [
            -18,
            46
        ],
        [
            -18,
            49
        ],
        [
            -16,
            55
        ],
        [
            -20,
            46
        ],
        [
            -24,
            51
        ],
        [
            -24,
            47
        ],
        [
            -24,
            43
        ],
        [
            -28,
            50
        ],
        [
            -32,
            54
        ],
        [
            -30,
            55
        ],
        [
            -28,
            52
        ],
        [
            -26,
            38
        ],
        [
            -28,
            46
        ],
        [
            -26,
            47
        ],
        [
            -28,
            52
        ],
        [
            -28,
            50
        ],
        [
            -26,
            52
        ],
        [
            -26,
            54
        ],
        [
            -24,
            53
        ],
        [
            -24,
            53
        ],
        [
            -26,
            59
        ]
    ],
    "timestamps": [
        0.5666666666666667,
        0.6,
        0.7,
        0.7333333333333333,
        0.8,
        0.8666666666666667,
        0.9,
        0.9333333333333333,
        0.9666666666666667,
        1.0,
        1.0333333333333332,
        1.1,
        1.3333333333333333,
        1.3666666666666667,
        1.4,
        1.4333333333333333,
        1.4666666666666666,
        1.5333333333333332,
        1.5666666666666667,
        1.6,
        1.6333333333333333,
        1.6666666666666667,
        1.7,
        1.7333333333333334,
        1.7666666666666666,
        1.8,
        1.8333333333333333,
        1.8666666666666667,
        1.9333333333333333,
        1.9666666666666666,
        2.0,
        2.033333333333333,
        2.0666666666666664,
        2.1,
        2.1333333333333333,
        2.1666666666666665,
        2.2,
        2.2333333333333334,
        2.2666666666666666,
        2.3,
        2.3333333333333335,
        2.3666666666666667,
        2.4,
        2.433333333333333,
        2.466666666666667,
        2.5,
        2.533333333333333,
        2.5666666666666664,
        2.6,
        2.6333333333333333,
        2.6666666666666665,
        2.7,
        2.7333333333333334,
        2.7666666666666666,
        2.8,
        2.8333333333333335,
        2.8666666666666667,
        2.9,
        2.933333333333333,
        2.966666666666667
    ],
    "total_coordinates": 60
}