{
    "metadata": {
        "video_path": "Videos/Clips/player9/part1/player9_part1_clip17_grade8.mp4",
        "video_name": "player9_part1_clip17_grade8",
        "player_id": 9,
        "part": 1,
        "clip": 17,
        "grade": 8,
        "duration": 3.0,
        "fps": 30.0,
        "frame_width": 1080,
        "frame_height": 1920,
        "total_frames": 90,
        "model": "mobilenet_thin",
        "resize": "0x0",
        "resize_out_ratio": 4.0,
        "reference_point": "Pelvis",
        "keypoints_used": [
            "Pelvis",
            "Left Shoulder",
            "Right Elbow",
            "Right Wrist"
        ],
        "interpolation_method": "linear",
        "interpolated_frames": 62,
        "processing_date": "2026-02-28T09:16:53.453103"
    },
    "Pelvis": [
        [
            570,
            910
        ],
        [
            562,
            910
        ],
        [
            556,
            908
        ],
        [
            552,
            912
        ],
        [
            546,
            919
        ],
        [
            544,
            926
        ],
        [
            542,
            934
        ],
        [
            540,
            938
        ],
        [
            538,
            942
        ],
        [
            536,
            944
        ],
        [
            532,
            942
        ],
        [
            530,
            936
        ],
        [
            524,
            926
        ],
        [
            524,
            919
        ],
        [
            522,
            919
        ],
        [
            514,
            914
        ],
        [
            506,
            914
        ],
        [
            496,
            914
        ],
        [
            488,
            914
        ],
        [
            482,
            918
        ],
        [
            474,
            922
        ],
        [
            468,
            919
        ],
        [
            460,
            923
        ],
        [
            474,
            923
        ],
        [
            470,
            927
        ],
        [
            462,
            930
        ],
        [
            458,
            932
        ],
        [
            446,
            936
        ],
        [
            436,
            938
        ],
        [
            428,
            936
        ],
        [
            422,
            934
        ],
        [
            414,
            927
        ],
        [
            410,
            927
        ],
        [
            402,
            922
        ],
        [
            394,
            922
        ],
        [
            388,
            923
        ],
        [
            382,
            919
        ],
        [
            380,
            918
        ],
        [
            368,
            914
        ],
        [
            366,
            914
        ],
        [
            360,
            914
        ],
        [
            360,
            914
        ],
        [
            356,
            918
        ],
        [
            354,
            914
        ],
        [
            350,
            918
        ],
        [
            350,
            918
        ],
        [
            328,
            918
        ],
        [
            322,
            919
        ],
        [
            320,
            919
        ],
        [
            318,
            922
        ],
        [
            322,
            923
        ],
        [
            322,
            926
        ],
        [
            322,
            926
        ],
        [
            324,
            926
        ],
        [
            316,
            926
        ],
        [
            324,
            923
        ],
        [
            328,
            922
        ],
        [
            328,
            919
        ],
        [
            330,
            918
        ],
        [
            332,
            918
        ],
        [
            336,
            919
        ],
        [
            338,
            922
        ],
        [
            340,
            926
        ],
        [
            344,
            930
        ],
        [
            346,
            938
        ],
        [
            348,
            942
        ],
        [
            350,
            944
        ],
        [
            354,
            946
        ],
        [
            356,
            944
        ],
        [
            360,
            942
        ],
        [
            362,
            936
        ],
        [
            366,
            930
        ],
        [
            370,
            923
        ],
        [
            373,
            918
        ],
        [
            382,
            916
        ],
        [
            388,
            914
        ],
        [
            396,
            912
        ],
        [
            402,
            912
        ],
        [
            410,
            912
        ],
        [
            418,
            914
        ],
        [
            424,
            918
        ],
        [
            428,
            918
        ],
        [
            434,
            926
        ],
        [
            438,
            930
        ],
        [
            444,
            934
        ],
        [
            448,
            940
        ],
        [
            454,
            942
        ],
        [
            458,
            942
        ],
        [
            466,
            934
        ]
    ],
    "Left Shoulder Original": [
        [
            602,
            1026
        ],
        [
            594,
            1021
        ],
        [
            588,
            1024
        ],
        [
            580,
            1026
        ],
        [
            574,
            1032
        ],
        [
            568,
            1038
        ],
        [
            560,
            1046
        ],
        [
            554,
            1050
        ],
        [
            548,
            1056
        ],
        [
            542,
            1055
        ],
        [
            536,
            1053
        ],
        [
            530,
            1052
        ],
        [
            526,
            1046
        ],
        [
            522,
            1036
        ],
        [
            512,
            1032
        ],
        [
            506,
            1028
        ],
        [
            500,
            1026
        ],
        [
            490,
            1026
        ],
        [
            484,
            1024
        ],
        [
            476,
            1021
        ],
        [
            468,
            1021
        ],
        [
            462,
            1021
        ],
        [
            456,
            1024
        ],
        [
            450,
            1026
        ],
        [
            440,
            1032
        ],
        [
            436,
            1034
        ],
        [
            424,
            1038
        ],
        [
            418,
            1040
        ],
        [
            412,
            1040
        ],
        [
            404,
            1036
        ],
        [
            396,
            1032
        ],
        [
            386,
            1028
        ],
        [
            382,
            1024
        ],
        [
            376,
            1021
        ],
        [
            370,
            1020
        ],
        [
            360,
            1018
        ],
        [
            352,
            1013
        ],
        [
            350,
            1010
        ],
        [
            344,
            1004
        ],
        [
            340,
            1002
        ],
        [
            338,
            999
        ],
        [
            338,
            999
        ],
        [
            334,
            999
        ],
        [
            336,
            1002
        ],
        [
            334,
            999
        ],
        [
            332,
            1002
        ],
        [
            332,
            1002
        ],
        [
            340,
            999
        ],
        [
            346,
            998
        ],
        [
            352,
            998
        ],
        [
            360,
            998
        ],
        [
            362,
            998
        ],
        [
            362,
            998
        ],
        [
            362,
            999
        ],
        [
            364,
            999
        ],
        [
            364,
            998
        ],
        [
            366,
            998
        ],
        [
            368,
            998
        ],
        [
            370,
            999
        ],
        [
            373,
            999
        ],
        [
            376,
            999
        ],
        [
            380,
            1002
        ],
        [
            386,
            1006
        ],
        [
            388,
            1010
        ],
        [
            394,
            1016
        ],
        [
            396,
            1024
        ],
        [
            398,
            1028
        ],
        [
            402,
            1029
        ],
        [
            406,
            1029
        ],
        [
            412,
            1026
        ],
        [
            414,
            1024
        ],
        [
            418,
            1018
        ],
        [
            424,
            1010
        ],
        [
            430,
            1008
        ],
        [
            436,
            1004
        ],
        [
            440,
            1006
        ],
        [
            448,
            1008
        ],
        [
            456,
            1008
        ],
        [
            462,
            1012
        ],
        [
            468,
            1013
        ],
        [
            472,
            1020
        ],
        [
            478,
            1024
        ],
        [
            480,
            1032
        ],
        [
            484,
            1038
        ],
        [
            488,
            1044
        ],
        [
            492,
            1050
        ],
        [
            496,
            1052
        ],
        [
            502,
            1050
        ],
        [
            506,
            1048
        ]
    ],
    "Left Shoulder Relative": [
        [
            32,
            116
        ],
        [
            32,
            111
        ],
        [
            32,
            116
        ],
        [
            28,
            114
        ],
        [
            28,
            113
        ],
        [
            24,
            112
        ],
        [
            18,
            112
        ],
        [
            14,
            112
        ],
        [
            10,
            114
        ],
        [
            6,
            111
        ],
        [
            4,
            111
        ],
        [
            0,
            116
        ],
        [
            2,
            120
        ],
        [
            -2,
            117
        ],
        [
            -10,
            113
        ],
        [
            -8,
            114
        ],
        [
            -6,
            112
        ],
        [
            -6,
            112
        ],
        [
            -4,
            110
        ],
        [
            -6,
            103
        ],
        [
            -6,
            99
        ],
        [
            -6,
            102
        ],
        [
            -4,
            101
        ],
        [
            -24,
            103
        ],
        [
            -30,
            105
        ],
        [
            -26,
            104
        ],
        [
            -34,
            106
        ],
        [
            -28,
            104
        ],
        [
            -24,
            102
        ],
        [
            -24,
            100
        ],
        [
            -26,
            98
        ],
        [
            -28,
            101
        ],
        [
            -28,
            97
        ],
        [
            -26,
            99
        ],
        [
            -24,
            98
        ],
        [
            -28,
            95
        ],
        [
            -30,
            94
        ],
        [
            -30,
            92
        ],
        [
            -24,
            90
        ],
        [
            -26,
            88
        ],
        [
            -22,
            85
        ],
        [
            -22,
            85
        ],
        [
            -22,
            81
        ],
        [
            -18,
            88
        ],
        [
            -16,
            81
        ],
        [
            -18,
            84
        ],
        [
            4,
            84
        ],
        [
            18,
            80
        ],
        [
            26,
            79
        ],
        [
            34,
            76
        ],
        [
            38,
            75
        ],
        [
            40,
            72
        ],
        [
            40,
            72
        ],
        [
            38,
            73
        ],
        [
            48,
            73
        ],
        [
            40,
            75
        ],
        [
            38,
            76
        ],
        [
            40,
            79
        ],
        [
            40,
            81
        ],
        [
            41,
            81
        ],
        [
            40,
            80
        ],
        [
            42,
            80
        ],
        [
            46,
            80
        ],
        [
            44,
            80
        ],
        [
            48,
            78
        ],
        [
            48,
            82
        ],
        [
            48,
            84
        ],
        [
            48,
            83
        ],
        [
            50,
            85
        ],
        [
            52,
            84
        ],
        [
            52,
            88
        ],
        [
            52,
            88
        ],
        [
            54,
            87
        ],
        [
            57,
            90
        ],
        [
            54,
            88
        ],
        [
            52,
            92
        ],
        [
            52,
            96
        ],
        [
            54,
            96
        ],
        [
            52,
            100
        ],
        [
            50,
            99
        ],
        [
            48,
            102
        ],
        [
            50,
            106
        ],
        [
            46,
            106
        ],
        [
            46,
            108
        ],
        [
            44,
            110
        ],
        [
            44,
            110
        ],
        [
            42,
            110
        ],
        [
            44,
            108
        ],
        [
            40,
            114
        ]
    ],
    "Right Elbow Original": [
        [
            520,
            961
        ],
        [
            522,
            968
        ],
        [
            510,
            972
        ],
        [
            504,
            988
        ],
        [
            498,
            994
        ],
        [
            498,
            1004
        ],
        [
            494,
            1018
        ],
        [
            488,
            1020
        ],
        [
            483,
            1022
        ],
        [
            478,
            1023
        ],
        [
            472,
            1025
        ],
        [
            466,
            1027
        ],
        [
            461,
            1028
        ],
        [
            456,
            1030
        ],
        [
            450,
            1032
        ],
        [
            444,
            1034
        ],
        [
            439,
            1036
        ],
        [
            434,
            1037
        ],
        [
            428,
            1039
        ],
        [
            422,
            1041
        ],
        [
            417,
            1042
        ],
        [
            412,
            1044
        ],
        [
            406,
            1046
        ],
        [
            400,
            1049
        ],
        [
            393,
            1051
        ],
        [
            387,
            1054
        ],
        [
            381,
            1056
        ],
        [
            375,
            1059
        ],
        [
            368,
            1061
        ],
        [
            362,
            1064
        ],
        [
            362,
            1058
        ],
        [
            342,
            1062
        ],
        [
            336,
            1056
        ],
        [
            328,
            1052
        ],
        [
            322,
            1049
        ],
        [
            316,
            1046
        ],
        [
            316,
            1036
        ],
        [
            311,
            1029
        ],
        [
            296,
            1028
        ],
        [
            299,
            1021
        ],
        [
            302,
            1013
        ],
        [
            305,
            1006
        ],
        [
            308,
            998
        ],
        [
            311,
            991
        ],
        [
            314,
            984
        ],
        [
            317,
            976
        ],
        [
            320,
            969
        ],
        [
            314,
            964
        ],
        [
            296,
            1002
        ],
        [
            278,
            1002
        ],
        [
            274,
            996
        ],
        [
            266,
            994
        ],
        [
            270,
            991
        ],
        [
            276,
            978
        ],
        [
            288,
            969
        ],
        [
            304,
            957
        ],
        [
            320,
            956
        ],
        [
            332,
            957
        ],
        [
            338,
            957
        ],
        [
            340,
            960
        ],
        [
            338,
            961
        ],
        [
            338,
            961
        ],
        [
            332,
            964
        ],
        [
            328,
            968
        ],
        [
            324,
            976
        ],
        [
            322,
            980
        ],
        [
            320,
            986
        ],
        [
            320,
            991
        ],
        [
            320,
            996
        ],
        [
            320,
            994
        ],
        [
            322,
            990
        ],
        [
            326,
            986
        ],
        [
            330,
            980
        ],
        [
            334,
            976
        ],
        [
            344,
            972
        ],
        [
            352,
            969
        ],
        [
            362,
            966
        ],
        [
            370,
            964
        ],
        [
            378,
            964
        ],
        [
            384,
            961
        ],
        [
            392,
            966
        ],
        [
            400,
            974
        ],
        [
            406,
            983
        ],
        [
            408,
            988
        ],
        [
            414,
            996
        ],
        [
            418,
            998
        ],
        [
            418,
            1002
        ],
        [
            420,
            999
        ],
        [
            424,
            996
        ]
    ],
    "Right Elbow Relative": [
        [
            -50,
            51
        ],
        [
            -40,
            58
        ],
        [
            -46,
            64
        ],
        [
            -48,
            76
        ],
        [
            -48,
            75
        ],
        [
            -46,
            78
        ],
        [
            -48,
            84
        ],
        [
            -52,
            82
        ],
        [
            -55,
            80
        ],
        [
            -58,
            79
        ],
        [
            -60,
            83
        ],
        [
            -64,
            91
        ],
        [
            -63,
            102
        ],
        [
            -68,
            111
        ],
        [
            -72,
            113
        ],
        [
            -70,
            120
        ],
        [
            -67,
            122
        ],
        [
            -62,
            123
        ],
        [
            -60,
            125
        ],
        [
            -60,
            123
        ],
        [
            -57,
            120
        ],
        [
            -56,
            125
        ],
        [
            -54,
            123
        ],
        [
            -74,
            126
        ],
        [
            -77,
            124
        ],
        [
            -75,
            124
        ],
        [
            -77,
            124
        ],
        [
            -71,
            123
        ],
        [
            -68,
            123
        ],
        [
            -66,
            128
        ],
        [
            -60,
            124
        ],
        [
            -72,
            135
        ],
        [
            -74,
            129
        ],
        [
            -74,
            130
        ],
        [
            -72,
            127
        ],
        [
            -72,
            123
        ],
        [
            -66,
            117
        ],
        [
            -69,
            111
        ],
        [
            -72,
            114
        ],
        [
            -67,
            107
        ],
        [
            -58,
            99
        ],
        [
            -55,
            92
        ],
        [
            -48,
            80
        ],
        [
            -43,
            77
        ],
        [
            -36,
            66
        ],
        [
            -33,
            58
        ],
        [
            -8,
            51
        ],
        [
            -8,
            45
        ],
        [
            -24,
            83
        ],
        [
            -40,
            80
        ],
        [
            -48,
            73
        ],
        [
            -56,
            68
        ],
        [
            -52,
            65
        ],
        [
            -48,
            52
        ],
        [
            -28,
            43
        ],
        [
            -20,
            34
        ],
        [
            -8,
            34
        ],
        [
            4,
            38
        ],
        [
            8,
            39
        ],
        [
            8,
            42
        ],
        [
            2,
            42
        ],
        [
            0,
            39
        ],
        [
            -8,
            38
        ],
        [
            -16,
            38
        ],
        [
            -22,
            38
        ],
        [
            -26,
            38
        ],
        [
            -30,
            42
        ],
        [
            -34,
            45
        ],
        [
            -36,
            52
        ],
        [
            -40,
            52
        ],
        [
            -40,
            54
        ],
        [
            -40,
            56
        ],
        [
            -40,
            57
        ],
        [
            -39,
            58
        ],
        [
            -38,
            56
        ],
        [
            -36,
            55
        ],
        [
            -34,
            54
        ],
        [
            -32,
            52
        ],
        [
            -32,
            52
        ],
        [
            -34,
            47
        ],
        [
            -32,
            48
        ],
        [
            -28,
            56
        ],
        [
            -28,
            57
        ],
        [
            -30,
            58
        ],
        [
            -30,
            62
        ],
        [
            -30,
            58
        ],
        [
            -36,
            60
        ],
        [
            -38,
            57
        ],
        [
            -42,
            62
        ]
    ],
    "Right Wrist Original": [
        [
            512,
            961
        ],
        [
            508,
            969
        ],
        [
            500,
            991
        ],
        [
            488,
            1002
        ],
        [
            480,
            1010
        ],
        [
            474,
            1028
        ],
        [
            468,
            1042
        ],
        [
            463,
            1044
        ],
        [
            458,
            1046
        ],
        [
            453,
            1048
        ],
        [
            448,
            1050
        ],
        [
            444,
            1053
        ],
        [
            439,
            1055
        ],
        [
            434,
            1057
        ],
        [
            429,
            1059
        ],
        [
            424,
            1061
        ],
        [
            419,
            1063
        ],
        [
            414,
            1065
        ],
        [
            410,
            1068
        ],
        [
            405,
            1070
        ],
        [
            400,
            1072
        ],
        [
            395,
            1074
        ],
        [
            390,
            1076
        ],
        [
            383,
            1078
        ],
        [
            376,
            1081
        ],
        [
            369,
            1083
        ],
        [
            363,
            1085
        ],
        [
            356,
            1087
        ],
        [
            349,
            1090
        ],
        [
            342,
            1092
        ],
        [
            337,
            1090
        ],
        [
            332,
            1088
        ],
        [
            326,
            1088
        ],
        [
            322,
            1082
        ],
        [
            313,
            1078
        ],
        [
            304,
            1074
        ],
        [
            298,
            1066
        ],
        [
            294,
            1048
        ],
        [
            276,
            1044
        ],
        [
            279,
            1033
        ],
        [
            282,
            1021
        ],
        [
            285,
            1010
        ],
        [
            288,
            999
        ],
        [
            292,
            987
        ],
        [
            295,
            976
        ],
        [
            298,
            965
        ],
        [
            301,
            953
        ],
        [
            304,
            942
        ],
        [
            308,
            1018
        ],
        [
            278,
            1024
        ],
        [
            246,
            1010
        ],
        [
            232,
            999
        ],
        [
            228,
            982
        ],
        [
            248,
            961
        ],
        [
            278,
            940
        ],
        [
            318,
            934
        ],
        [
            348,
            942
        ],
        [
            366,
            946
        ],
        [
            376,
            956
        ],
        [
            382,
            961
        ],
        [
            380,
            964
        ],
        [
            378,
            966
        ],
        [
            378,
            968
        ],
        [
            372,
            969
        ],
        [
            362,
            968
        ],
        [
            356,
            969
        ],
        [
            348,
            972
        ],
        [
            344,
            974
        ],
        [
            340,
            972
        ],
        [
            338,
            972
        ],
        [
            340,
            968
        ],
        [
            342,
            964
        ],
        [
            344,
            961
        ],
        [
            350,
            956
        ],
        [
            358,
            953
        ],
        [
            364,
            952
        ],
        [
            372,
            953
        ],
        [
            380,
            952
        ],
        [
            388,
            949
        ],
        [
            398,
            949
        ],
        [
            404,
            952
        ],
        [
            408,
            960
        ],
        [
            408,
            968
        ],
        [
            414,
            972
        ],
        [
            416,
            978
        ],
        [
            420,
            982
        ],
        [
            422,
            982
        ],
        [
            426,
            980
        ],
        [
            428,
            980
        ]
    ],
    "Right Wrist Relative": [
        [
            -58,
            51
        ],
        [
            -54,
            59
        ],
        [
            -56,
            83
        ],
        [
            -64,
            90
        ],
        [
            -66,
            91
        ],
        [
            -70,
            102
        ],
        [
            -74,
            108
        ],
        [
            -77,
            106
        ],
        [
            -80,
            104
        ],
        [
            -83,
            104
        ],
        [
            -84,
            108
        ],
        [
            -86,
            117
        ],
        [
            -85,
            129
        ],
        [
            -90,
            138
        ],
        [
            -93,
            140
        ],
        [
            -90,
            147
        ],
        [
            -87,
            149
        ],
        [
            -82,
            151
        ],
        [
            -78,
            154
        ],
        [
            -77,
            152
        ],
        [
            -74,
            150
        ],
        [
            -73,
            155
        ],
        [
            -70,
            153
        ],
        [
            -91,
            155
        ],
        [
            -94,
            154
        ],
        [
            -93,
            153
        ],
        [
            -95,
            153
        ],
        [
            -90,
            151
        ],
        [
            -87,
            152
        ],
        [
            -86,
            156
        ],
        [
            -85,
            156
        ],
        [
            -82,
            161
        ],
        [
            -84,
            161
        ],
        [
            -80,
            160
        ],
        [
            -81,
            156
        ],
        [
            -84,
            151
        ],
        [
            -84,
            147
        ],
        [
            -86,
            130
        ],
        [
            -92,
            130
        ],
        [
            -87,
            119
        ],
        [
            -78,
            107
        ],
        [
            -75,
            96
        ],
        [
            -68,
            81
        ],
        [
            -62,
            73
        ],
        [
            -55,
            58
        ],
        [
            -52,
            47
        ],
        [
            -27,
            35
        ],
        [
            -18,
            23
        ],
        [
            -12,
            99
        ],
        [
            -40,
            102
        ],
        [
            -76,
            87
        ],
        [
            -90,
            73
        ],
        [
            -94,
            56
        ],
        [
            -76,
            35
        ],
        [
            -38,
            14
        ],
        [
            -6,
            11
        ],
        [
            20,
            20
        ],
        [
            38,
            27
        ],
        [
            46,
            38
        ],
        [
            50,
            43
        ],
        [
            44,
            45
        ],
        [
            40,
            44
        ],
        [
            38,
            42
        ],
        [
            28,
            39
        ],
        [
            16,
            30
        ],
        [
            8,
            27
        ],
        [
            -2,
            28
        ],
        [
            -10,
            28
        ],
        [
            -16,
            28
        ],
        [
            -22,
            30
        ],
        [
            -22,
            32
        ],
        [
            -24,
            34
        ],
        [
            -26,
            38
        ],
        [
            -23,
            38
        ],
        [
            -24,
            37
        ],
        [
            -24,
            38
        ],
        [
            -24,
            41
        ],
        [
            -22,
            40
        ],
        [
            -22,
            37
        ],
        [
            -20,
            35
        ],
        [
            -20,
            34
        ],
        [
            -20,
            42
        ],
        [
            -26,
            42
        ],
        [
            -24,
            42
        ],
        [
            -28,
            44
        ],
        [
            -28,
            42
        ],
        [
            -32,
            40
        ],
        [
            -32,
            38
        ],
        [
            -38,
            46
        ]
    ],
    "timestamps": [
        0.03333333333333333,
        0.06666666666666667,
        0.1,
        0.13333333333333333,
        0.16666666666666666,
        0.2,
        0.23333333333333334,
        0.26666666666666666,
        0.3,
        0.3333333333333333,
        0.36666666666666664,
        0.4,
        0.43333333333333335,
        0.4666666666666667,
        0.5,
        0.5333333333333333,
        0.5666666666666667,
        0.6,
        0.6333333333333333,
        0.6666666666666666,
        0.7,
        0.7333333333333333,
        0.7666666666666666,
        0.8,
        0.8333333333333334,
        0.8666666666666667,
        0.9,
        0.9333333333333333,
        0.9666666666666667,
        1.0,
        1.0333333333333332,
        1.0666666666666667,
        1.1,
        1.1333333333333333,
        1.1666666666666667,
        1.2,
        1.2333333333333334,
        1.2666666666666666,
        1.3,
        1.3333333333333333,
        1.3666666666666667,
        1.4,
        1.4333333333333333,
        1.4666666666666666,
        1.5,
        1.5333333333333332,
        1.5666666666666667,
        1.6,
        1.6333333333333333,
        1.6666666666666667,
        1.7,
        1.7333333333333334,
        1.7666666666666666,
        1.8,
        1.8333333333333333,
        1.8666666666666667,
        1.9,
        1.9333333333333333,
        1.9666666666666666,
        2.0,
        2.033333333333333,
        2.0666666666666664,
        2.1,
        2.1333333333333333,
        2.1666666666666665,
        2.2,
        2.2333333333333334,
        2.2666666666666666,
        2.3,
        2.3333333333333335,
        2.3666666666666667,
        2.4,
        2.433333333333333,
        2.466666666666667,
        2.5,
        2.533333333333333,
        2.5666666666666664,
        2.6,
        2.6333333333333333,
        2.6666666666666665,
        2.7,
        2.7333333333333334,
        2.7666666666666666,
        2.8,
        2.8333333333333335,
        2.8666666666666667,
        2.9,
        2.933333333333333,
        2.966666666666667
    ],
    "total_coordinates": 89
}